you/__init__.py
you/__main__.py
you/main.py
you/version.py
you/tests/__init__.py
you/utils/__init__.py
you/utils/config.py
you/utils/logging.py
you/utils/python_compat.py
you/wrappers/__init__.py
you/wrappers/chromium.py
you/wrappers/ffmpeg.py
you-0.5.0.dev1.dist-info/DESCRIPTION.rst
you-0.5.0.dev1.dist-info/METADATA
you-0.5.0.dev1.dist-info/RECORD
you-0.5.0.dev1.dist-info/WHEEL
you-0.5.0.dev1.dist-info/entry_points.txt
you-0.5.0.dev1.dist-info/metadata.json
you-0.5.0.dev1.dist-info/top_level.txt
